Metadata-Version: 1.0
Name: SaeedMatrixCalculation
Version: 0.0.1
Summary: Add, Subtract, Multiply and Invert Matrices
Home-page: UNKNOWN
Author: Saeed AlSarhi
Author-email: saeedalsarhi@gmail.com
License: UNKNOWN
Platform: UNKNOWN
